{
    "fields": {
        "channel": {
            "visible": {
                "conditionGroup": [
                    {
                        "type": "isTrue",
                        "attribute": "isInbound"
                    }
                ]
            }
        },
        "instructions": {
            "visible": {
                "conditionGroup": [
                    {
                        "type": "isTrue",
                        "attribute": "isInbound"
                    }
                ]
            }
        }
    }
}
